Plotter/__init__.py
Plotter/plotter.py
Plotter/version.py
csvplotter/__init__.py
csvplotter/plotter.py
csvplotter/version.py
csvplotter-0.0.6.4.5.dist-info/LICENSE
csvplotter-0.0.6.4.5.dist-info/METADATA
csvplotter-0.0.6.4.5.dist-info/WHEEL
csvplotter-0.0.6.4.5.dist-info/top_level.txt
csvplotter-0.0.6.4.5.dist-info/RECORD
