Metadata-Version: 2.1
Name: csvplotter
Version: 0.0.6.4.5
Summary: Plotter using .csv filesWritten by pedrohenriquecoimbra
Home-page: https://github.com/pedrohenriquecoimbra/csvplotter
Author: Pedro Henrique Coimbra
Author-email: pedro-henrique.herig-coimbra@inrae.fr
License: MIT
Keywords: csv,plot,figure,image,graph,data
Platform: any
Classifier: Development Status :: 4 - Beta
Classifier: Environment :: Other Environment
Classifier: Framework :: Jupyter
Classifier: Intended Audience :: Science/Research
Classifier: Programming Language :: Python
Classifier: Programming Language :: Python :: 3
Classifier: Programming Language :: Python :: 3.8
Classifier: Programming Language :: Python :: 3.9
Classifier: Programming Language :: Python :: 3.10
Classifier: Programming Language :: Python :: 3.11
Classifier: Programming Language :: Python :: 3.12
Classifier: Programming Language :: Python :: 3.13
Classifier: Programming Language :: Python :: 3.14
Classifier: Topic :: Other/Nonlisted Topic
Requires-Python: >=3.8
License-File: LICENSE
Requires-Dist: pandas (>=2.0.0)
Requires-Dist: matplotlib (>=3.1.0)
Requires-Dist: seaborn (>=0.9.0)
